lib_funciones/__init__.py
lib_funciones/funciones.py
lib_funciones-0.0.2.dist-info/METADATA
lib_funciones-0.0.2.dist-info/WHEEL
lib_funciones-0.0.2.dist-info/top_level.txt
lib_funciones-0.0.2.dist-info/RECORD
